pynhole/__init__.py
pynhole/binary_pairs_kv.py
pynhole/markov.py
pynhole/naive_bayes_graph.py
pynhole/pairs_pot.py
pynhole/pot.py
pynhole/old/__init__.py
pynhole/old/naive_binary_network.py
pynhole/pstan/__init__.py
pynhole/pstan/io.py
pynhole/pstan/models_scripts/__init__.py
pynhole/pstan/models_scripts/mixture_of_two_binomials.py
pynhole-0.0.3.dist-info/LICENSE
pynhole-0.0.3.dist-info/METADATA
pynhole-0.0.3.dist-info/WHEEL
pynhole-0.0.3.dist-info/top_level.txt
pynhole-0.0.3.dist-info/RECORD
