Metadata-Version: 2.1
Name: pynhole
Version: 0.0.3
Summary: Probabilistic Inference tools.
Home-page: https://github.com/thorwhalen/newut/tree/master/pynhole
Author: Thor Whalen
License: mit
Platform: any
License-File: LICENSE
